ampal/ampal_warnings.py
ampal/nucleic_acid.py
ampal/dssp.py
ampal/naccess.py
ampal/align.py
ampal/amino_acids.py
ampal/mmcif_parser.py
ampal/__init__.py
ampal/base_ampal.py
ampal/geometry.c
ampal/protein.py
ampal/assembly.py
ampal/ligands.py
ampal/geometry.cpython-313-darwin.so
ampal/py.typed
ampal/analyse_protein.py
ampal/pdb_parser.py
ampal/interactions.py
ampal/pseudo_atoms.py
ampal/data.py
ampal/geometry.pyx
ampal/datafiles/chemical_elements.json
ampal/datafiles/amino_acids.json
ampal/datafiles/pdb_atom_column_format.json
ampal-2.1.1.dist-info/RECORD
ampal-2.1.1.dist-info/WHEEL
ampal-2.1.1.dist-info/top_level.txt
ampal-2.1.1.dist-info/METADATA
ampal-2.1.1.dist-info/licenses/LICENSE
