Metadata-Version: 2.4
Name: ampal
Version: 2.1.1
Summary: A framework for representing biomolecular structure.
Maintainer-email: ChrisWellsWood <cwwoodesq@gmail.com>
License: MIT License
Project-URL: Homepage, https://github.com/isambard-uob/ampal
Classifier: Intended Audience :: Science/Research
Classifier: License :: OSI Approved :: MIT License
Classifier: Natural Language :: English
Classifier: Topic :: Scientific/Engineering :: Bio-Informatics
Requires-Python: >=3.8
License-File: LICENSE
Requires-Dist: cython
Requires-Dist: networkx
Requires-Dist: numpy
Dynamic: license-file
